MediaSwift/__init__.py
MediaSwift/ffpe.py
MediaSwift/ffpl.py
MediaSwift/ffpr.py
MediaSwift/bin/ffpe.exe
MediaSwift/bin/ffpl.exe
MediaSwift/bin/ffpr.exe
MediaSwift-2.4.2.dist-info/LICENSE.txt
MediaSwift-2.4.2.dist-info/METADATA
MediaSwift-2.4.2.dist-info/WHEEL
MediaSwift-2.4.2.dist-info/entry_points.txt
MediaSwift-2.4.2.dist-info/top_level.txt
MediaSwift-2.4.2.dist-info/RECORD
