Metadata-Version: 2.1
Name: MediaSwift
Version: 2.4.2
Summary: A MediaSwift PYTHON PACKAGE FOR MEDIA CONVERSION PLAY AND PROBING.
Home-page: https://github.com/ROHIT-SINGH-1/PYTHON-MEDIASWIFT.git
Author: ROHIT SINGH
Author-email: rs3232263@gmail.com
License: MIT
Project-URL: Documentation, https://github.com/ROHIT-SINGH-1/PYTHON-MEDIASWIFT/blob/main/README.md
Project-URL: Source Code, https://github.com/ROHIT-SINGH-1/PYTHON-MEDIASWIFT
Project-URL: Bug Tracker, https://github.com/ROHIT-SINGH-1/PYTHON-MEDIASWIFT/issues
Keywords: MEDIA VIDEO CONVERSION PROBING AND PLAYING.
Classifier: Development Status :: 5 - Production/Stable
Classifier: Intended Audience :: Developers
Classifier: Intended Audience :: End Users/Desktop
Classifier: Programming Language :: Python :: 3
Classifier: License :: OSI Approved :: MIT License
Classifier: Operating System :: OS Independent
Classifier: Topic :: Multimedia :: Video
Classifier: Topic :: Software Development :: Libraries :: Python Modules
Requires-Python: >=3.8
License-File: LICENSE.txt
Requires-Dist: rich
Requires-Dist: tqdm
Requires-Dist: numpy
